reputils/MailReport.py
reputils/__init__.py
reputils/py.typed
reputils-0.0.16.dist-info/METADATA
reputils-0.0.16.dist-info/WHEEL
reputils-0.0.16.dist-info/RECORD
