Metadata-Version: 2.4
Name: reputils
Version: 0.0.16
Summary: reputils
Project-URL: Homepage, https://github.com/vroomfondel/reputils
Project-URL: Repository, https://github.com/vroomfondel/reputils
Project-URL: Issues, https://github.com/vroomfondel/reputils/issues
Author-email: Henning Thieß <ht@xomox.cc>
Keywords: dateutil,email,logging,loguru,mail-report,python,pytz,smtp,utilities
Classifier: Development Status :: 5 - Production/Stable
Classifier: License :: OSI Approved :: GNU Lesser General Public License v3 or later (LGPLv3+)
Classifier: Operating System :: OS Independent
Classifier: Programming Language :: Python :: 3
Classifier: Programming Language :: Python :: 3.12
Classifier: Topic :: Communications :: Email
Classifier: Topic :: Communications :: Email :: Email Clients (MUA)
Classifier: Topic :: Internet
Classifier: Topic :: Software Development :: Libraries
Classifier: Topic :: Software Development :: Libraries :: Python Modules
Requires-Python: >=3.12
Requires-Dist: loguru>=0.7.3
Requires-Dist: python-dateutil==2.9.*
Requires-Dist: pytz>=2025.2
